vvpet/__init__.py
vvpet/vvpet_main.py
vvpet-0.5.2.dist-info/METADATA
vvpet-0.5.2.dist-info/WHEEL
vvpet-0.5.2.dist-info/RECORD
