Metadata-Version: 2.3
Name: vvpet
Version: 0.5.2
Summary: Your little friend
Author: Vojtech Velebny
Author-email: velebnyvo@gymla.cz
Requires-Python: >=3.11
Classifier: Programming Language :: Python :: 3
Classifier: Programming Language :: Python :: 3.11
Classifier: Programming Language :: Python :: 3.12
Classifier: Programming Language :: Python :: 3.13
